user/__init__.py
user/ott_platform.py
my_ott_package-1.0.0.dist-info/License.txt
my_ott_package-1.0.0.dist-info/METADATA
my_ott_package-1.0.0.dist-info/WHEEL
my_ott_package-1.0.0.dist-info/top_level.txt
my_ott_package-1.0.0.dist-info/RECORD
