Metadata-Version: 2.1
Name: my-ott-package
Version: 1.0.0
Summary: StreamSights OTT Platform User Class
Author: shreyas
License-File: License.txt
